{
  "Workflows": [
    {
      "Path": null,
      "SortBy": 0,
      "VariablesSectionElementsOrder": [],
      "ArgumentsSectionElementsOrder": null,
      "ConstantsSectionElementsOrder": [],
      "AddedNamespaces": null
    },
    {
      "Path": "Main.xaml",
      "SortBy": 0,
      "VariablesSectionElementsOrder": [
        "google_api_key&Parallel_1",
        "google_api_key&TryCatch_2",
        "dt_Result&Sequence_1",
        "InvoiceNum&TryCatch_1",
        "InvoiceDate&TryCatch_1",
        "InvoiceCustomerName&TryCatch_1",
        "InvoiceTotal&TryCatch_1",
        "InvoiceCustomerID&TryCatch_1"
      ],
      "ArgumentsSectionElementsOrder": [],
      "ConstantsSectionElementsOrder": [],
      "AddedNamespaces": null
    }
  ]
}